README.md
setup.cfg
setup.py
pycore/__init__.py
pycore/api.py
pycore/cloud.py
pycore/utils.py
pycore.egg-info/PKG-INFO
pycore.egg-info/SOURCES.txt
pycore.egg-info/dependency_links.txt
pycore.egg-info/requires.txt
pycore.egg-info/top_level.txt
pycore/extensions/__init__.py
pycore/extensions/coredhcp/__init__.py
pycore/extensions/coredhcp/models/__init__.py
pycore/extensions/coredhcp/models/network.py
pycore/extensions/coretalk/__init__.py
pycore/extensions/coretalk/api.py
pycore/extensions/coretalk/models/__init__.py
pycore/extensions/coretalk/models/userdata.py
pycore/extensions/corevpn/__init__.py
pycore/extensions/corevpn/api.py
pycore/extensions/corevpn/models/__init__.py
pycore/extensions/corevpn/models/vpn.py
pycore/extensions/thunderscript/__init__.py
pycore/extensions/thunderscript/api.py
pycore/models/__init__.py
pycore/models/base_model.py
pycore/models/image.py
pycore/models/lease.py
pycore/models/network.py
pycore/models/network_pool.py
pycore/models/permission.py
pycore/models/task.py
pycore/models/template.py
pycore/models/token.py
pycore/models/vm.py
tests/0000_install_core.py
tests/0000_install_nfs_storage.py
tests/0000_install_node.py
tests/0000_load_initial_data.py
tests/0000_setup_coredhcp.py
tests/0000_setup_coretalk.py
tests/0000_setup_coreui.py
tests/0000_setup_corevpn.py
tests/0001_register.py
tests/0002_account_info.py
tests/0002_account_network_quota.py
tests/0002_api.py
tests/0002_check_resources.py
tests/0002_permissions.py
tests/0002_permissions_token.py
tests/0002_template_caps.py
tests/0002_validation.py
tests/0003_image_create_invalid_format.py
tests/0003_image_permanent.py
tests/0003_image_transient.py
tests/0003_image_upload.py
tests/0003_image_upload_data.py
tests/0003_image_upload_invalid_format.py
tests/0004_vm_create.py
tests/0004_vm_edit.py
tests/0004_vm_fill_cluster.py
tests/0004_vm_reload.py
tests/0004_vm_resize.py
tests/0004_vm_start_poweroff.py
tests/0005_network_allocation.py
tests/0005_network_isolated_allocate.py
tests/0005_network_isolated_create.py
tests/0005_network_pools.py
tests/0005_network_redirection_lease.py
tests/0005_network_routed_allocate.py
