Metadata-Version: 1.1
Name: pycore
Version: 17.4.17
Summary: CoreCluster API Library
Home-page: http://cloudover.org/pycore/
Author: Maciej & Marta Nabozny
Author-email: mn@mnabozny.pl
License: UNKNOWN
Download-URL: https://github.com/cloudOver/PyCloud/archive/master.zip
Keywords: corecluster,overcluster,cloudover,cloud
Platform: UNKNOWN
